{
  "id": "Data_Processing",
  "title": "Data Processing",
  "description": "Data processing involves transforming raw data into a structured format that is suitable for analysis and visualization. Chimera provides tools and capabilities to support data processing workflows, including data transformation, orchestration, and monitoring.",
  "source": "@site/docs/Data_Processing.md",
  "sourceDirName": ".",
  "slug": "/Data_Processing",
  "permalink": "/docs/Data_Processing",
  "draft": false,
  "unlisted": false,
  "editUrl": "https://github.com/facebook/docusaurus/tree/main/packages/create-docusaurus/templates/shared/docs/Data_Processing.md",
  "tags": [],
  "version": "current",
  "frontMatter": {},
  "sidebar": "tutorialSidebar",
  "previous": {
    "title": "Data Ingestion",
    "permalink": "/docs/Data_Ingestion"
  },
  "next": {
    "title": "Data Science and Machine Learning",
    "permalink": "/docs/Data_Science_and_Machine_Learning"
  }
}